datahugger/__init__.py
datahugger/datahugger.abi3.so
datahugger/datahugger.pyi
datahugger.libs/libgcc_s-f685abf1.so.1
datahugger_ng-0.1.1.dist-info/METADATA
datahugger_ng-0.1.1.dist-info/WHEEL
datahugger_ng-0.1.1.dist-info/RECORD
