Metadata-Version: 2.4
Name: datahugger-ng
Version: 0.1.1
Classifier: Programming Language :: Rust
Classifier: Programming Language :: Python :: Implementation :: CPython
Classifier: Programming Language :: Python :: Implementation :: PyPy
Requires-Dist: pytest~=8.3 ; extra == 'tests'
Requires-Dist: pytest-asyncio~=1.3 ; extra == 'tests'
Provides-Extra: tests
Summary: python binding of datahugger -- rust tool for fetching data and metadata from DOI or URL.
Home-Page: https://github.com/EOSC-Data-Commons/datahugger-rs
License-Expression: MIT AND Apache-2.0
Requires-Python: >=3.10
